{
    "I go to the cinema": "Je vais au cinéma",
    "you go to the market (singular)": "tu vas au marché",
    "he goes to university": "il va à l'université",
    "we go to eat": "nous allons manger",
    "you guys go to the grocery store": "vous allez à l'épicerie",
    "they go (she)": "elles vont",
    "I take the bus": "je prends le bus",
    "you take a coffee": "tu prends un café",
    "he takes a shower": "il prend une douche",
    "we take the transports": "nous prenons les transports",
    "you take (plural)": "vous prenez",
    "they take (he)": "ils prennent",
    "I make a tart": "je fais une tarte",
    "she does the homework": "elle fait les devoirs",
    "you do the grocery (singular)": "tu fais les courses",
    "they do sports (he)": "ils font du sport",
    "we do": "nous faisons",
    "you do (plural)": "vous faites",
    "do swimming": "faire de la natation",
    "do skiing": "faire du ski",
    "do climbing": "faire de l'escalade",
    "do martial arts": "faire des arts martiaux",
    "play the tennis": "jouer au tennis",
    "play the petanque": "jouer à la pétanque",
    "he does music": "il fait de la musique",
    "she plays the guitar": "elle joue de la guitare",
    "in": "dans",
    "in between": "entre",
    "next to": "à côté de",
    "opposite across from": "en face de",
    "in front of": "devant",
    "behind": "derrière",
    "on": "sur",
    "under": "sous",
    "near": "près de",
    "far": "loin de",
    "left of": "à gauche de",
    "right of": "à droite de"
}